seq_tools/__init__.py
seq_tools/cli.py
seq_tools/dataframe.py
seq_tools/dot_bracket.py
seq_tools/extinction_coeff.py
seq_tools/logger.py
seq_tools/sequence.py
seq_tools/structure.py
rna_seq_tools-0.7.1.dist-info/LICENSE
rna_seq_tools-0.7.1.dist-info/METADATA
rna_seq_tools-0.7.1.dist-info/WHEEL
rna_seq_tools-0.7.1.dist-info/entry_points.txt
rna_seq_tools-0.7.1.dist-info/top_level.txt
rna_seq_tools-0.7.1.dist-info/RECORD
