Metadata-Version: 2.1
Name: rna-seq-tools
Version: 0.7.1
Summary: simple functions for manipulating sequences and secondary structures in pandas dataframe format
Home-page: https://github.com/jyesselm/seq_tools
Author: Joe Yesselman
Author-email: jyesselm@unl.edu
Keywords: seq_tools
Classifier: Intended Audience :: Developers
Classifier: Natural Language :: English
Classifier: Programming Language :: Python :: 3
Classifier: Programming Language :: Python :: Implementation :: PyPy
License-File: LICENSE
Requires-Dist: wheel (>=0.22)
Requires-Dist: black
Requires-Dist: click
Requires-Dist: editdistance
Requires-Dist: tabulate
Requires-Dist: numpy
Requires-Dist: pandas
Requires-Dist: pytest
Requires-Dist: vienna
